fukobabatekkral/__init__.py
fukobabatekkral/__main__.py
fukobabatekkral/_version.py
fukobabatekkral/cli/__init__.py
fukobabatekkral/cli/main.py
fukobabatekkral/core/__init__.py
fukobabatekkral/core/fukobabatekkral.py
fukobabatekkral/core/validator.py
fukobabatekkral/resources/commands/claude/sp-continue.md
fukobabatekkral/resources/commands/claude/sp-decompose.md
fukobabatekkral/resources/commands/claude/sp-execute.md
fukobabatekkral/resources/commands/claude/sp-plan.md
fukobabatekkral/resources/commands/claude/sp-pulse.md
fukobabatekkral/resources/commands/claude/sp-spec.md
fukobabatekkral/resources/commands/claude/sp-status.md
fukobabatekkral/resources/commands/claude/sp-task.md
fukobabatekkral/resources/commands/gemini/sp-continue.toml
fukobabatekkral/resources/commands/gemini/sp-decompose.toml
fukobabatekkral/resources/commands/gemini/sp-execute.toml
fukobabatekkral/resources/commands/gemini/sp-plan.toml
fukobabatekkral/resources/commands/gemini/sp-pulse.toml
fukobabatekkral/resources/commands/gemini/sp-spec.toml
fukobabatekkral/resources/commands/gemini/sp-status.toml
fukobabatekkral/resources/commands/gemini/sp-task.toml
fukobabatekkral/resources/memory/constitution.md
fukobabatekkral/resources/memory/context.md
fukobabatekkral/resources/memory/decisions.md
fukobabatekkral/resources/scripts/sp-pulse-decompose.ps1
fukobabatekkral/resources/scripts/sp-pulse-decompose.sh
fukobabatekkral/resources/scripts/sp-pulse-execute.ps1
fukobabatekkral/resources/scripts/sp-pulse-execute.sh
fukobabatekkral/resources/scripts/sp-pulse-init.ps1
fukobabatekkral/resources/scripts/sp-pulse-init.sh
fukobabatekkral/resources/scripts/sp-pulse-plan.ps1
fukobabatekkral/resources/scripts/sp-pulse-plan.sh
fukobabatekkral/resources/scripts/sp-pulse-spec.ps1
fukobabatekkral/resources/scripts/sp-pulse-spec.sh
fukobabatekkral/resources/scripts/sp-pulse-task.ps1
fukobabatekkral/resources/scripts/sp-pulse-task.sh
fukobabatekkral/resources/templates/plan.md
fukobabatekkral-1.4.5.dist-info/licenses/LICENSE
fukobabatekkral-1.4.5.dist-info/METADATA
fukobabatekkral-1.4.5.dist-info/WHEEL
fukobabatekkral-1.4.5.dist-info/entry_points.txt
fukobabatekkral-1.4.5.dist-info/top_level.txt
fukobabatekkral-1.4.5.dist-info/RECORD
