Metadata-Version: 2.4
Name: fukobabatekkral
Version: 1.4.5
Summary: Specification-Driven Development Framework
Home-page: https://github.com/fukobabatekkral
Author: FukobabaTekKral
Author-email: 
Maintainer: FukobabaTekKral
License: MIT
Project-URL: Homepage, https://github.com/fukobabatekkral
Project-URL: Repository, https://github.com/fukobabatekkral/fukobabatekkral
Project-URL: Issues, https://github.com/fukobabatekkral/fukobabatekkral/issues
Project-URL: Documentation, https://github.com/fukobabatekkral/fukobabatekkral/wiki
Project-URL: Changelog, https://github.com/fukobabatekkral/fukobabatekkral/releases
Keywords: development,specification,ai,claude,gemini,automation,framework,cli
Classifier: Development Status :: 4 - Beta
Classifier: Intended Audience :: Developers
Classifier: Topic :: Software Development :: Build Tools
Classifier: Topic :: Software Development :: Code Generators
Classifier: Topic :: Software Development :: Documentation
Classifier: License :: OSI Approved :: MIT License
Classifier: Programming Language :: Python :: 3
Classifier: Programming Language :: Python :: 3.11
Classifier: Programming Language :: Python :: 3.12
Classifier: Operating System :: OS Independent
Requires-Python: >=3.11
License-File: LICENSE
Requires-Dist: pyyaml>=6.0
Requires-Dist: click>=8.0
Requires-Dist: rich>=13.0
Requires-Dist: jinja2>=3.0
Requires-Dist: gitpython>=3.1
Requires-Dist: toml>=0.10
Requires-Dist: packaging>=21.0
Provides-Extra: dev
Requires-Dist: pytest>=7.0; extra == "dev"
Requires-Dist: pytest-cov>=4.0; extra == "dev"
Requires-Dist: black>=23.0; extra == "dev"
Requires-Dist: flake8>=6.0; extra == "dev"
Requires-Dist: mypy>=1.0; extra == "dev"
Requires-Dist: pre-commit>=3.0; extra == "dev"
Dynamic: home-page
Dynamic: license-file
Dynamic: requires-python
